fxacli/__init__.py
fxacli/cli.py
fxacli-1.1.0.dist-info/DESCRIPTION.rst
fxacli-1.1.0.dist-info/METADATA
fxacli-1.1.0.dist-info/RECORD
fxacli-1.1.0.dist-info/WHEEL
fxacli-1.1.0.dist-info/entry_points.txt
fxacli-1.1.0.dist-info/metadata.json
fxacli-1.1.0.dist-info/top_level.txt
